pycorebaz/__init__.py
pycorebaz/mx/__init__.py
pycorebaz/mx/com/__init__.py
pycorebaz/mx/com/bancoazteca/__init__.py
pycorebaz/mx/com/bancoazteca/cloud/__init__.py
pycorebaz/mx/com/bancoazteca/cloud/configuracion/Configuracion.py
pycorebaz/mx/com/bancoazteca/cloud/configuracion/__init__.py
pycorebaz/mx/com/bancoazteca/cloud/core/__init__.py
pycorebaz/mx/com/bancoazteca/cloud/core/db/Database.py
pycorebaz/mx/com/bancoazteca/cloud/core/db/DatabaseAWS.py
pycorebaz/mx/com/bancoazteca/cloud/core/db/DatabaseAWSPostgreSQL.py
pycorebaz/mx/com/bancoazteca/cloud/core/db/__init__.py
pycorebaz/mx/com/bancoazteca/cloud/core/db/utilidades_bd.py
pycorebaz/mx/com/bancoazteca/cloud/core/handlers/Error_Handler.py
pycorebaz/mx/com/bancoazteca/cloud/core/handlers/__init__.py
pycorebaz/mx/com/bancoazteca/cloud/core/log/Level.py
pycorebaz/mx/com/bancoazteca/cloud/core/log/Log.py
pycorebaz/mx/com/bancoazteca/cloud/core/log/__init__.py
pycorebaz/mx/com/bancoazteca/cloud/core/models/CodigosRespuesta.py
pycorebaz/mx/com/bancoazteca/cloud/core/models/DB.py
pycorebaz/mx/com/bancoazteca/cloud/core/models/Daos.py
pycorebaz/mx/com/bancoazteca/cloud/core/models/TipoConsulta.py
pycorebaz/mx/com/bancoazteca/cloud/core/models/TipoInputOutput.py
pycorebaz/mx/com/bancoazteca/cloud/core/models/__init__.py
pycorebaz/mx/com/bancoazteca/cloud/core/seguridad/Apigee.py
pycorebaz/mx/com/bancoazteca/cloud/core/seguridad/Crypto.py
pycorebaz/mx/com/bancoazteca/cloud/core/seguridad/LlavesCobranza.py
pycorebaz/mx/com/bancoazteca/cloud/core/seguridad/Middleware.py
pycorebaz/mx/com/bancoazteca/cloud/core/seguridad/MiddlewareApigee.py
pycorebaz/mx/com/bancoazteca/cloud/core/seguridad/__init__.py
pycorebaz/mx/com/bancoazteca/cloud/core/utilerias/Cadenas.py
pycorebaz/mx/com/bancoazteca/cloud/core/utilerias/Constantes.py
pycorebaz/mx/com/bancoazteca/cloud/core/utilerias/Request.py
pycorebaz/mx/com/bancoazteca/cloud/core/utilerias/Web.py
pycorebaz/mx/com/bancoazteca/cloud/core/utilerias/__init__.py
pycorebaz-0.0.12.dist-info/licenses/LICENSE.txt
pycorebaz-0.0.12.dist-info/METADATA
pycorebaz-0.0.12.dist-info/WHEEL
pycorebaz-0.0.12.dist-info/top_level.txt
pycorebaz-0.0.12.dist-info/RECORD
